doxs/__init__.py
doxs/_validation.py
doxs/core.py
doxs/py.typed
doxs/schema.json
doxs-0.5.0.dist-info/LICENSE
doxs-0.5.0.dist-info/METADATA
doxs-0.5.0.dist-info/WHEEL
doxs-0.5.0.dist-info/RECORD
